Workbook

Sheet Dashboard Summary
A1: Tata Motors Financial Ratio Model
A2: Executive summary dashboard for the Tata Motors Financial Performance & Business Health Analysis project. Units are INR crore unless stated otherwise.
A4: Latest Year KPI | B4: FY2025 | C4: Interpretation | E4: Key Project Takeaways
A5: Revenue from Operations | B5: ='Income Statement'!F5 -> 439695 | C5: Topline scale of Tata Motors Group | E5: Revenue recovered strongly from FY2021 levels and reached its highest level in FY2025.
A6: Profit After Tax | B6: ='Income Statement'!F18 -> 28149 | C6: Bottom-line profitability | E6: Profitability turned around from losses in FY2021-FY2022 to positive PAT from FY2023 onward.
A7: Net Profit Margin | B7: ='Financial Ratios'!F5 -> 0.064019377 | C7: Profit generated per rupee of revenue | E7: Leverage reduced materially by FY2025, supporting a stronger business health score.
A8: Current Ratio | B8: ='Financial Ratios'!F11 -> 0.95876629 | C8: Short-term liquidity position | E8: Cash flow strength remains an important driver to monitor because auto free cash flow supports reinvestment and debt control.
A9: Debt-to-Equity Ratio | B9: ='Financial Ratios'!F14 -> 0.50914023 | C9: Leverage position
A10: Operating Cash Flow Margin | B10: ='Financial Ratios'!F16 -> 0.14351312 | C10: Cash conversion from operations
A11: Auto Free Cash Flow | B11: ='Cash Flow Statement'!F9 -> 22348 | C11: Cash left after automotive investment needs
A12: Business Health Score | B12: ='Business Health Scorecard'!F10 -> 75 | C12: Overall model score out of 100
A15: Financial Year | B15: FY2021 | C15: FY2022 | D15: FY2023 | E15: FY2024 | F15: FY2025
A16: Revenue | B16: ='Income Statement'!B5 -> 249794.75 | C16: ='Income Statement'!C5 -> 278453.62 | D16: ='Income Statement'!D5 -> 345966.97 | E16: ='Income Statement'!E5 -> 437927.77 | F16: ='Income Statement'!F5 -> 439695
A17: PAT | B17: ='Income Statement'!B18 -> -13395.1 | C17: ='Income Statement'!C18 -> -11308.76 | D17: ='Income Statement'!D18 -> 2689.87 | E17: ='Income Statement'!E18 -> 31806.75 | F17: ='Income Statement'!F18 -> 28149
A18: Net Profit Margin | B18: ='Financial Ratios'!B5 -> -0.053624426 | C18: ='Financial Ratios'!C5 -> -0.040612724 | D18: ='Financial Ratios'!D5 -> 0.007774933 | E18: ='Financial Ratios'!E5 -> 0.072630128 | F18: ='Financial Ratios'!F5 -> 0.064019377
A19: Debt-to-Equity | B19: ='Financial Ratios'!B14 -> 2.0199778 | C19: ='Financial Ratios'!C14 -> 2.8603412 | D19: ='Financial Ratios'!D14 -> 2.3890046 | E19: ='Financial Ratios'!E14 -> 1.0580721 | F19: ='Financial Ratios'!F14 -> 0.50914023
A20: Health Score | B20: ='Business Health Scorecard'!B10 -> 47 | C20: ='Business Health Scorecard'!C10 -> 43 | D20: ='Business Health Scorecard'!D10 -> 57 | E20: ='Business Health Scorecard'!E10 -> 78 | F20: ='Business Health Scorecard'!F10 -> 75

Sheet Income Statement
A1: Income Statement
A2: Consolidated Tata Motors figures. Unit: INR crore. Blue values are hardcoded source inputs extracted from annual reports.
A4: Metric | B4: FY2021 | C4: FY2022 | D4: FY2023 | E4: FY2024 | F4: FY2025
A5: Revenue from Operations | B5: 249794.75 | C5: 278453.62 | D5: 345966.97 | E5: 437927.77 | F5: 439695
A6: Other Income | B6: 2643.19 | C6: 3053.63 | D6: 4633.18 | E6: 5949.92 | F6: 6244
A7: Total Income | B7: 252437.94 | C7: 281507.25 | D7: 350600.15 | E7: 443877.69 | F7: 445939
A8: Cost of Materials Consumed | B8: 141357.27 | C8: 160920.56 | D8: 208944.31 | E8: 249277.79 | F8: 241148
A9: Purchase of Products for Sale | B9: 12250.09 | C9: 18374.77 | D9: 22306.95 | E9: 25043.44 | F9: 27802
A10: Employee Benefits Expense | B10: 27648.48 | C10: 30808.52 | D10: 33654.7 | E10: 42486.64 | F10: 47767
A11: Finance Costs | B11: 8097.17 | C11: 9311.86 | D11: 10225.48 | E11: 9985.76 | F11: 5083
A12: Depreciation & Amortisation Expense | B12: 23546.71 | C12: 24835.69 | D12: 24860.36 | E12: 27270.13 | F12: 23256
A13: Product Development / Engineering Expenses | B13: 5226.63 | C13: 9209.5 | D13: 10661.96 | E13: 10958.72 | F13: 10716
A14: Other Expenses | B14: 40921.97 | C14: 47133.85 | D14: 61785.96 | E14: 78874.98 | F14: 85399
A15: Total Expenses | B15: 249151.2 | C15: 287881.08 | D15: 349133.13 | E15: 415645.32 | F15: 411896
A16: Profit Before Tax | B16: -10474.28 | C16: -7003.41 | D16: 3057.55 | E16: 27955.11 | F16: 33780
... A18: Profit After Tax / Profit for Year | B18: -13395.1 | C18: -11308.76 | D18: 2689.87 | E18: 31806.75 | F18: 28149

Sheet Balance Sheet
A1: Balance Sheet
A2: Consolidated year-end balance sheet figures. Unit: INR crore. Blue values are hardcoded source inputs extracted from annual reports.
A4: Metric | B4: FY2021 | C4: FY2022 | D4: FY2023 | E4: FY2024 | F4: FY2025
A5: Total Assets | B5: 343125.8 | C5: 330619.93 | D5: 336081.38 | E5: 370663.96 | F5: 378642
A6: Total Equity | B6: 56820.21 | C6: 48832.3 | D6: 52599.51 | E6: 93093.93 | F6: 122754
A7: Total Non-Current Assets | B7: 196238.16 | C7: 183642.39 | D7: 184552.91 | E7: 202271.81 | F7: 218317
A8: Current Assets | B8: 146666.84 | C8: 146453.69 | D8: 150700.69 | E8: 167718.24 | F8: 159811
A9: Cash and Cash Equivalents | B9: 31700.01 | C9: 38159.01 | D9: 31886.95 | E9: 40014.76 | F9: 34349
A10: Current Investments | B10: 19051.19 | C10: 22709.22 | D10: 18838.31 | E10: 14253.24 | F10: 27199
A11: Total Non-Current Liabilities | B11: 128556.41 | C11: 131104.82 | D11: 128454.54 | E11: 103953.03 | F11: 89204
A12: Current Liabilities | B12: 157749.18 | C12: 150682.81 | D12: 155027.33 | E12: 173617 | F12: 166684
A13: Non-Current Borrowings | B13: 93112.77 | C13: 97759.17 | D13: 88695.81 | E13: 62148.53 | F13: 40217
A14: Current Borrowings | B14: 21662.79 | C14: 41917.87 | D14: 36964.66 | E14: 36351.56 | F14: 22282

Sheet Cash Flow Statement
A1: Cash Flow Statement
A2: Consolidated cash flow figures. Unit: INR crore. Blue values are hardcoded source inputs extracted from annual reports.
A4: Metric | B4: FY2021 | C4: FY2022 | D4: FY2023 | E4: FY2024 | F4: FY2025
A5: Net Cash from Operating Activities | B5: 29000.51 | C5: 14282.83 | D5: 35388.01 | E5: 67915.36 | F5: 63102
A6: Net Cash Used in Investing Activities | B6: -26126.25 | C6: -4775.12 | D6: -16804.16 | E6: -22828.09 | F6: -47594
A7: Net Cash from Financing Activities | B7: 9904.2 | C7: -3380.17 | D7: -26242.9 | E7: -37005.99 | F7: -18786
A8: Total Capex Payments | B8: -20205.4 | C8: -15168.42 | D8: -18095.68 | E8: -31413.63 | F8: -38042
A9: Auto Free Cash Flow | B9: 5317 | C9: -9254 | D9: 7840 | E9: 26924 | F9: 22348
A10: Closing Cash and Cash Equivalents | B10: 31700.01 | C10: 38159.01 | D10: 31886.95 | E10: 40014.76 | F10: 34349

Sheet Financial Ratios
A1: Financial Ratios
A2: Formula-driven analysis sheet. Green formula cells link to the statement sheets in this workbook.
A4: Metric | B4: FY2021 | C4: FY2022 | D4: FY2023 | E4: FY2024 | F4: FY2025
A5: Net Profit Margin | B5: ='Income Statement'!B18/'Income Statement'!B5 -> -0.053624426 | C5: ='Income Statement'!C18/'Income Statement'!C5 -> -0.040612724 | D5: ='Income Statement'!D18/'Income Statement'!D5 -> 0.007774933 | E5: ='Income Statement'!E18/'Income Statement'!E5 -> 0.072630128 | F5: ='Income Statement'!F18/'Income Statement'!F5 -> 0.064019377
A6: PBT Margin | B6: ='Income Statement'!B16/'Income Statement'!B5 -> -0.041931546 | C6: ='Income Statement'!C16/'Income Statement'!C5 -> -0.025151083 | D6: ='Income Statement'!D16/'Income Statement'!D5 -> 0.0088376934 | E6: ='Income Statement'!E16/'Income Statement'!E5 -> 0.063834979 | F6: ='Income Statement'!F16/'Income Statement'!F5 -> 0.076825982
A7: Expense-to-Income Ratio | B7: ='Income Statement'!B15/'Income Statement'!B7 -> 0.98698001 | C7: ='Income Statement'!C15/'Income Statement'!C7 -> 1.0226418 | D7: ='Income Statement'!D15/'Income Statement'!D7 -> 0.99581569 | E7: ='Income Statement'!E15/'Income Statement'!E7 -> 0.93639606 | F7: ='Income Statement'!F15/'Income Statement'!F7 -> 0.92365996
A8: Return on Assets (ROA) | B8: ='Income Statement'!B18/'Balance Sheet'!B5 -> -0.039038452 | C8: ='Income Statement'!C18/AVERAGE('Balance Sheet'!B5,'Balance Sheet'!C5) -> -0.033569816 | D8: ='Income Statement'!D18/AVERAGE('Balance Sheet'!C5,'Balance Sheet'!D5) -> 0.0080691907 | E8: ='Income Statement'!E18/AVERAGE('Balance Sheet'!D5,'Balance Sheet'!E5) -> 0.090009083 | F8: ='Income Statement'!F18/AVERAGE('Balance Sheet'!E5,'Balance Sheet'!F5) -> 0.075133528
A9: Return on Equity (ROE) | B9: ='Income Statement'!B18/'Balance Sheet'!B6 -> -0.23574534 | C9: ='Income Statement'!C18/AVERAGE('Balance Sheet'!B6,'Balance Sheet'!C6) -> -0.21407461 | D9: ='Income Statement'!D18/AVERAGE('Balance Sheet'!C6,'Balance Sheet'!D6) -> 0.053037997 | E9: ='Income Statement'!E18/AVERAGE('Balance Sheet'!D6,'Balance Sheet'!E6) -> 0.4366257 | F9: ='Income Statement'!F18/AVERAGE('Balance Sheet'!E6,'Balance Sheet'!F6) -> 0.26082252
A10: Asset Turnover Ratio | B10: ='Income Statement'!B5/'Balance Sheet'!B5 -> 0.72799757 | C10: ='Income Statement'!C5/AVERAGE('Balance Sheet'!B5,'Balance Sheet'!C5) -> 0.8265837 | D10: ='Income Statement'!D5/AVERAGE('Balance Sheet'!C5,'Balance Sheet'!D5) -> 1.037847 | E10: ='Income Statement'!E5/AVERAGE('Balance Sheet'!D5,'Balance Sheet'!E5) -> 1.2392802 | F10: ='Income Statement'!F5/AVERAGE('Balance Sheet'!E5,'Balance Sheet'!F5) -> 1.173606
A11: Current Ratio | B11: ='Balance Sheet'!B8/'Balance Sheet'!B12 -> 0.92974708 | C11: ='Balance Sheet'!C8/'Balance Sheet'!C12 -> 0.97193363 | D11: ='Balance Sheet'!D8/'Balance Sheet'!D12 -> 0.97209111 | E11: ='Balance Sheet'!E8/'Balance Sheet'!E12 -> 0.96602429 | F11: ='Balance Sheet'!F8/'Balance Sheet'!F12 -> 0.95876629
A12: Cash Ratio | B12: =('Balance Sheet'!B9+'Balance Sheet'!B10)/'Balance Sheet'!B12 -> 0.32172085 | C12: =('Balance Sheet'!C9+'Balance Sheet'!C10)/'Balance Sheet'!C12 -> 0.4039494 | D12: =('Balance Sheet'!D9+'Balance Sheet'!D10)/'Balance Sheet'!D12 -> 0.32720205 | E12: =('Balance Sheet'!E9+'Balance Sheet'!E10)/'Balance Sheet'!E12 -> 0.31257308 | F12: =('Balance Sheet'!F9+'Balance Sheet'!F10)/'Balance Sheet'!F12 -> 0.3692496
A13: Working Capital (INR crore) | B13: ='Balance Sheet'!B8-'Balance Sheet'!B12 -> -11082.34 | C13: ='Balance Sheet'!C8-'Balance Sheet'!C12 -> -4229.12 | D13: ='Balance Sheet'!D8-'Balance Sheet'!D12 -> -4326.64 | E13: ='Balance Sheet'!E8-'Balance Sheet'!E12 -> -5898.76 | F13: ='Balance Sheet'!F8-'Balance Sheet'!F12 -> -6873
A14: Debt-to-Equity Ratio | B14: =('Balance Sheet'!B13+'Balance Sheet'!B14)/'Balance Sheet'!B6 -> 2.0199778 | C14: =('Balance Sheet'!C13+'Balance Sheet'!C14)/'Balance Sheet'!C6 -> 2.8603412 | D14: =('Balance Sheet'!D13+'Balance Sheet'!D14)/'Balance Sheet'!D6 -> 2.3890046 | E14: =('Balance Sheet'!E13+'Balance Sheet'!E14)/'Balance Sheet'!E6 -> 1.0580721 | F14: =('Balance Sheet'!F13+'Balance Sheet'!F14)/'Balance Sheet'!F6 -> 0.50914023
A15: Debt Ratio | B15: =('Balance Sheet'!B11+'Balance Sheet'!B12)/'Balance Sheet'!B5 -> 0.83440415 | C15: =('Balance Sheet'!C11+'Balance Sheet'!C12)/'Balance Sheet'!C5 -> 0.8523008 | D15: =('Balance Sheet'!D11+'Balance Sheet'!D12)/'Balance Sheet'!D5 -> 0.84349175 | E15: =('Balance Sheet'!E11+'Balance Sheet'!E12)/'Balance Sheet'!E5 -> 0.74884548 | F15: =('Balance Sheet'!F11+'Balance Sheet'!F12)/'Balance Sheet'!F5 -> 0.67580459
A16: Operating Cash Flow Margin | B16: ='Cash Flow Statement'!B5/'Income Statement'!B5 -> 0.11609736 | C16: ='Cash Flow Statement'!C5/'Income Statement'!C5 -> 0.05129339 | D16: ='Cash Flow Statement'!D5/'Income Statement'!D5 -> 0.10228725 | E16: ='Cash Flow Statement'!E5/'Income Statement'!E5 -> 0.15508347 | F16: ='Cash Flow Statement'!F5/'Income Statement'!F5 -> 0.14351312
A17: Free Cash Flow Margin | B17: ='Cash Flow Statement'!B9/'Income Statement'!B5 -> 0.021285475 | C17: ='Cash Flow Statement'!C9/'Income Statement'!C5 -> -0.033233542 | D17: ='Cash Flow Statement'!D9/'Income Statement'!D5 -> 0.022661123 | E17: ='Cash Flow Statement'!E9/'Income Statement'!E5 -> 0.061480458 | F17: ='Cash Flow Statement'!F9/'Income Statement'!F5 -> 0.050826141
A18: Capex-to-Revenue Ratio | B18: =ABS('Cash Flow Statement'!B8)/'Income Statement'!B5 -> 0.080888009 | C18: =ABS('Cash Flow Statement'!C8)/'Income Statement'!C5 -> 0.054473776 | D18: =ABS('Cash Flow Statement'!D8)/'Income Statement'!D5 -> 0.052304646 | E18: =ABS('Cash Flow Statement'!E8)/'Income Statement'!E5 -> 0.071732446 | F18: =ABS('Cash Flow Statement'!F8)/'Income Statement'!F5 -> 0.086519064

Sheet Growth Analysis
A1: Growth Analysis
A2: Formula-driven year-on-year growth analysis based on the financial statements and ratios.
A4: Metric | B4: FY2021 | C4: FY2022 | D4: FY2023 | E4: FY2024 | F4: FY2025
A5: Revenue Growth | B5: - | C5: ='Income Statement'!C5/'Income Statement'!B5-1 -> 0.11472967 | D5: ='Income Statement'!D5/'Income Statement'!C5-1 -> 0.24245815 | E5: ='Income Statement'!E5/'Income Statement'!D5-1 -> 0.26580803 | F5: ='Income Statement'!F5/'Income Statement'!E5-1 -> 0.0040354372
A6: PAT Growth | B6: - | C6: ='Income Statement'!C18/'Income Statement'!B18-1 -> -0.15575397 | D6: ='Income Statement'!D18/'Income Statement'!C18-1 -> -1.2378572 | E6: ='Income Statement'!E18/'Income Statement'!D18-1 -> 10.824642 | F6: ='Income Statement'!F18/'Income Statement'!E18-1 -> -0.11499917
A7: Total Assets Growth | B7: - | C7: ='Balance Sheet'!C5/'Balance Sheet'!B5-1 -> -0.036446895 | D7: ='Balance Sheet'!D5/'Balance Sheet'!C5-1 -> 0.016518817 | E7: ='Balance Sheet'!E5/'Balance Sheet'!D5-1 -> 0.10289942 | F7: ='Balance Sheet'!F5/'Balance Sheet'!E5-1 -> 0.021523646
A8: Total Borrowings Growth | B8: - | C8: =(('Balance Sheet'!C13+'Balance Sheet'!C14)/('Balance Sheet'!B13+'Balance Sheet'!B14))-1 -> 0.21695804 | D8: =(('Balance Sheet'!D13+'Balance Sheet'!D14)/('Balance Sheet'!C13+'Balance Sheet'!C14))-1 -> -0.10034985 | E8: =(('Balance Sheet'!E13+'Balance Sheet'!E14)/('Balance Sheet'!D13+'Balance Sheet'!D14))-1 -> -0.216141 | F8: =(('Balance Sheet'!F13+'Balance Sheet'!F14)/('Balance Sheet'!E13+'Balance Sheet'!E14))-1 -> -0.36549297
A9: Operating Cash Flow Growth | B9: - | C9: ='Cash Flow Statement'!C5/'Cash Flow Statement'!B5-1 -> -0.50749728 | D9: ='Cash Flow Statement'!D5/'Cash Flow Statement'!C5-1 -> 1.4776609 | E9: ='Cash Flow Statement'!E5/'Cash Flow Statement'!D5-1 -> 0.91916302 | F9: ='Cash Flow Statement'!F5/'Cash Flow Statement'!E5-1 -> -0.070872922
A10: Auto Free Cash Flow Growth | B10: - | C10: ='Cash Flow Statement'!C9/'Cash Flow Statement'!B9-1 -> -2.7404551 | D10: ='Cash Flow Statement'!D9/'Cash Flow Statement'!C9-1 -> -1.8472012 | E10: ='Cash Flow Statement'!E9/'Cash Flow Statement'!D9-1 -> 2.4341837 | F10: ='Cash Flow Statement'!F9/'Cash Flow Statement'!E9-1 -> -0.16995989
A11: Business Health Score Change | B11: - | C11: -6.4 | D11: 7.7 | E11: 42.5 | F11: -17.2

Sheet Business Health Scorecard
A1: Business Health Scorecard
A2: Scoring model out of 100 using profitability, liquidity, debt control, cash flow strength, and growth quality.
A4: Component | B4: FY2021 | C4: FY2022 | D4: FY2023 | E4: FY2024 | F4: FY2025
A5: Profitability Strength | B5: =IF('Financial Ratios'!B5>5%,20,IF('Financial Ratios'!B5>0%,12,4)) -> 4 | C5: =IF('Financial Ratios'!C5>5%,20,IF('Financial Ratios'!C5>0%,12,4)) -> 4 | D5: =IF('Financial Ratios'!D5>5%,20,IF('Financial Ratios'!D5>0%,12,4)) -> 12 | E5: =IF('Financial Ratios'!E5>5%,20,IF('Financial Ratios'!E5>0%,12,4)) -> 20 | F5: =IF('Financial Ratios'!F5>5%,20,IF('Financial Ratios'!F5>0%,12,4)) -> 20
A6: Liquidity Strength | B6: =IF('Financial Ratios'!B11>=1.2,20,IF('Financial Ratios'!B11>=1,14,8)) -> 8 | C6: =IF('Financial Ratios'!C11>=1.2,20,IF('Financial Ratios'!C11>=1,14,8)) -> 8 | D6: =IF('Financial Ratios'!D11>=1.2,20,IF('Financial Ratios'!D11>=1,14,8)) -> 8 | E6: =IF('Financial Ratios'!E11>=1.2,20,IF('Financial Ratios'!E11>=1,14,8)) -> 8 | F6: =IF('Financial Ratios'!F11>=1.2,20,IF('Financial Ratios'!F11>=1,14,8)) -> 8
A7: Debt Control | B7: =IF('Financial Ratios'!B14<0.5,20,IF('Financial Ratios'!B14<1,15,IF('Financial Ratios'!B14<2,10,5))) -> 5 | C7: =IF('Financial Ratios'!C14<0.5,20,IF('Financial Ratios'!C14<1,15,IF('Financial Ratios'!C14<2,10,5))) -> 5 | D7: =IF('Financial Ratios'!D14<0.5,20,IF('Financial Ratios'!D14<1,15,IF('Financial Ratios'!D14<2,10,5))) -> 5 | E7: =IF('Financial Ratios'!E14<0.5,20,IF('Financial Ratios'!E14<1,15,IF('Financial Ratios'!E14<2,10,5))) -> 10 | F7: =IF('Financial Ratios'!F14<0.5,20,IF('Financial Ratios'!F14<1,15,IF('Financial Ratios'!F14<2,10,5))) -> 15
A8: Cash Flow Strength | B8: =IF('Financial Ratios'!B16>10%,20,IF('Financial Ratios'!B16>5%,14,8)) -> 20 | C8: =IF('Financial Ratios'!C16>10%,20,IF('Financial Ratios'!C16>5%,14,8)) -> 14 | D8: =IF('Financial Ratios'!D16>10%,20,IF('Financial Ratios'!D16>5%,14,8)) -> 20 | E8: =IF('Financial Ratios'!E16>10%,20,IF('Financial Ratios'!E16>5%,14,8)) -> 20 | F8: =IF('Financial Ratios'!F16>10%,20,IF('Financial Ratios'!F16>5%,14,8)) -> 20
A9: Growth Quality | B9: =10 -> 10 | C9: =IF(AND('Growth Analysis'!C5>0,'Growth Analysis'!C6>0),20,IF('Growth Analysis'!C5>0,12,6)) -> 12 | D9: =IF(AND('Growth Analysis'!D5>0,'Growth Analysis'!D6>0),20,IF('Growth Analysis'!D5>0,12,6)) -> 12 | E9: =IF(AND('Growth Analysis'!E5>0,'Growth Analysis'!E6>0),20,IF('Growth Analysis'!E5>0,12,6)) -> 20 | F9: =IF(AND('Growth Analysis'!F5>0,'Growth Analysis'!F6>0),20,IF('Growth Analysis'!F5>0,12,6)) -> 12
A10: Total Business Health Score | B10: =SUM(B5:B9) -> 47 | C10: =SUM(C5:C9) -> 43 | D10: =SUM(D5:D9) -> 57 | E10: =SUM(E5:E9) -> 78 | F10: =SUM(F5:F9) -> 75
A11: Health Rating | B11: =IF(B10>=80,"Strong",IF(B10>=60,"Moderate","Weak")) -> Weak | C11: =IF(C10>=80,"Strong",IF(C10>=60,"Moderate","Weak")) -> Weak | D11: =IF(D10>=80,"Strong",IF(D10>=60,"Moderate","Weak")) -> Weak | E11: =IF(E10>=80,"Strong",IF(E10>=60,"Moderate","Weak")) -> Moderate | F11: =IF(F10>=80,"Strong",IF(F10>=60,"Moderate","Weak")) -> Moderate
A13: Scoring Logic
A14: Profitability: Net profit margin > 5% = 20, > 0% = 12, otherwise 4
A15: Liquidity: Current ratio >= 1.2 = 20, >= 1.0 = 14, otherwise 8
A16: Debt Control: Debt-to-equity < 0.5 = 20, < 1.0 = 15, < 2.0 = 10, otherwise 5
A17: Cash Flow: Operating cash flow margin > 10% = 20, > 5% = 14, otherwise 8
A18: Growth Quality: revenue and PAT both improving = 20, revenue improving = 12, otherwise 6

Sheet Source Notes
A1: Source Notes
A2: Plain-text source URLs and file names used for the model inputs.
A4: Source Type | B4: File / URL | C4: Use in Workbook
A5: Annual Reports Page | B5: https://www.tatamotors.com/annual-reports/ | C5: Source for FY2021-FY2025 integrated annual reports
A6: FY2020-21 Annual Report | B6: tata-motor-IAR-2020-21.pdf | C6: FY2021 consolidated income statement, balance sheet and cash flow inputs
A7: FY2021-22 Annual Report | B7: tata-motor-IAR-2021-22.pdf | C7: FY2022 consolidated income statement, balance sheet and cash flow inputs
A8: FY2022-23 Annual Report | B8: tata-motor-IAR-2022-23.pdf | C8: FY2023 consolidated income statement, balance sheet and cash flow inputs
A9: FY2023-24 Annual Report | B9: tata-motor-IAR-2023-24.pdf | C9: FY2024 consolidated income statement, balance sheet and cash flow inputs
A10: FY2024-25 Annual Report | B10: tata-motor-IAR-2024-25.pdf | C10: FY2025 consolidated income statement, balance sheet and cash flow inputs
A11: Model Note | B11: Blue font = hardcoded source input; green font = workbook links/formulas; values are in INR crore unless marked as ratios or percentages. | C11: Formatting and model convention
